O365_notifications/__init__.py
O365_notifications/base.py
O365_notifications/constants.py
O365_notifications/push.py
O365_notifications/streaming.py
O365_notifications/utils.py
o365_notifications-0.1.1.dist-info/LICENSE
o365_notifications-0.1.1.dist-info/WHEEL
o365_notifications-0.1.1.dist-info/METADATA
o365_notifications-0.1.1.dist-info/RECORD
