Metadata-Version: 2.1
Name: o365-notifications
Version: 0.1.1
Summary: Pythonic handler for O365 Streaming & Push Notifications
Home-page: https://github.com/rena2damas/O365-notifications
License: MIT
Keywords: O365,notifications,push,streaming,flask,python,python3
Author: Renato Damas
Author-email: rena2damas@gmail.com
Requires-Python: >=3.9,<4.0
Classifier: Intended Audience :: Developers
Classifier: License :: OSI Approved :: MIT License
Classifier: Natural Language :: English
Classifier: Programming Language :: Python :: 3
Classifier: Programming Language :: Python :: 3.10
Classifier: Programming Language :: Python :: 3.9
Provides-Extra: O365
Requires-Dist: O365 (>=2.0.19,<3.0.0); extra == "O365"
Requires-Dist: marshmallow (>=3.17.0,<4.0.0)
Requires-Dist: requests (>=2.28.1,<3.0.0)
Project-URL: Repository, https://github.com/rena2damas/O365-notifications
Project-URL: issues, https://github.com/rena2damas/O365-notifications/issues
